c1_cs/__init__.py
c1_cs/mymodule.py
c1_cs-0.1.0.dist-info/METADATA
c1_cs-0.1.0.dist-info/WHEEL
c1_cs-0.1.0.dist-info/top_level.txt
c1_cs-0.1.0.dist-info/RECORD
