Metadata-Version: 2.2
Name: c1_cs
Version: 0.1.0
Summary: A Python package
Author-email: Annie Thomas <annie.thomas1@ibm.com>
Requires-Python: >=3.6
